ds_protocol_http_py_lib/__init__.py
ds_protocol_http_py_lib/enums.py
ds_protocol_http_py_lib/py.typed
ds_protocol_http_py_lib/resource.yaml
ds_protocol_http_py_lib/dataset/__init__.py
ds_protocol_http_py_lib/dataset/http.py
ds_protocol_http_py_lib/linked_service/__init__.py
ds_protocol_http_py_lib/linked_service/http.py
ds_protocol_http_py_lib/utils/__init__.py
ds_protocol_http_py_lib/utils/json_utils.py
ds_protocol_http_py_lib/utils/http/__init__.py
ds_protocol_http_py_lib/utils/http/config.py
ds_protocol_http_py_lib/utils/http/provider.py
ds_protocol_http_py_lib/utils/http/token_bucket.py
ds_protocol_http_py_lib-0.1.0a4.dist-info/licenses/LICENSE-APACHE
ds_protocol_http_py_lib-0.1.0a4.dist-info/METADATA
ds_protocol_http_py_lib-0.1.0a4.dist-info/WHEEL
ds_protocol_http_py_lib-0.1.0a4.dist-info/entry_points.txt
ds_protocol_http_py_lib-0.1.0a4.dist-info/top_level.txt
ds_protocol_http_py_lib-0.1.0a4.dist-info/RECORD
